df_fuzzy_merge/__init__.py
df_fuzzy_merge/df_fuzzy_merge.py
df_fuzzy_merge-0.0.5.dist-info/LICENSE
df_fuzzy_merge-0.0.5.dist-info/METADATA
df_fuzzy_merge-0.0.5.dist-info/WHEEL
df_fuzzy_merge-0.0.5.dist-info/top_level.txt
df_fuzzy_merge-0.0.5.dist-info/RECORD
