Metadata-Version: 2.1
Name: df-fuzzy-merge
Version: 0.0.5
Summary: Package that fuzzy merges two dataframes
Home-page: https://github.com/mmcelhan/df_fuzzy_merge
Author: Matthew McElhaney
Author-email: matt@lamplightlab.com
License: UNKNOWN
Project-URL: blog post, https://lamplightlab.com/2022/01/12/dataframe-fuzzy-matching/
Platform: UNKNOWN
Classifier: Programming Language :: Python :: 3
Classifier: License :: OSI Approved :: MIT License
Classifier: Operating System :: OS Independent
Requires-Python: >=3.6
License-File: LICENSE
Requires-Dist: ntlk
Requires-Dist: pandas
Requires-Dist: python-Levenshtein
Requires-Dist: fuzzywuzzy
